sparse_emb_util-0.2.2.dist-info/METADATA
sparse_emb_util-0.2.2.dist-info/WHEEL
sparse_emb_util-0.2.2.dist-info/licenses/LICENSE
sparse_emb_util/__init__.py
sparse_emb_util/__init__.pyi
sparse_emb_util/py.typed
sparse_emb_util/sparse_emb_util.cpython-39-x86_64-linux-gnu.so
sparse_emb_util-0.2.2.dist-info/RECORD
