Metadata-Version: 2.4
Name: sparse_emb_util
Version: 0.2.2
Classifier: Programming Language :: Rust
Classifier: Programming Language :: Python :: Implementation :: CPython
Classifier: Programming Language :: Python :: Implementation :: PyPy
License-File: LICENSE
Summary: Utilities for sparse embedding processing using Rust + Python.
Author-email: Guangyuan Ma <Ma787639046@outlook.com>
License-Expression: Apache-2.0
Requires-Python: >=3.8
